{
  "systems": [
    {
      "id": "1 22 31",
      "key": "000010002200031",
      "coords": {
        "x": 1,
        "y": 22,
        "z": 31
      }
    },
    {
      "id": "2 26 22",
      "key": "000020002600022",
      "coords": {
        "x": 2,
        "y": 26,
        "z": 22
      }
    },
    {
      "id": "2 27 22",
      "key": "000020002700022",
      "coords": {
        "x": 2,
        "y": 27,
        "z": 22
      }
    },
    {
      "id": "4 32 16",
      "key": "000040003200016",
      "coords": {
        "x": 4,
        "y": 32,
        "z": 16
      }
    },
    {
      "id": "4 37 20",
      "key": "000040003700020",
      "coords": {
        "x": 4,
        "y": 37,
        "z": 20
      }
    },
    {
      "id": "5 28 14",
      "key": "000050002800014",
      "coords": {
        "x": 5,
        "y": 28,
        "z": 14
      }
    },
    {
      "id": "7 15 38",
      "key": "000070001500038",
      "coords": {
        "x": 7,
        "y": 15,
        "z": 38
      }
    },
    {
      "id": "7 18 34",
      "key": "000070001800034",
      "coords": {
        "x": 7,
        "y": 18,
        "z": 34
      }
    },
    {
      "id": "8 17 19",
      "key": "000080001700019",
      "coords": {
        "x": 8,
        "y": 17,
        "z": 19
      }
    },
    {
      "id": "9 16 29",
      "key": "000090001600029",
      "coords": {
        "x": 9,
        "y": 16,
        "z": 29
      }
    },
    {
      "id": "9 19 16",
      "key": "000090001900016",
      "coords": {
        "x": 9,
        "y": 19,
        "z": 16
      }
    },
    {
      "id": "9 20 39",
      "key": "000090002000039",
      "coords": {
        "x": 9,
        "y": 20,
        "z": 39
      }
    },
    {
      "id": "9 29 18",
      "key": "000090002900018",
      "coords": {
        "x": 9,
        "y": 29,
        "z": 18
      }
    },
    {
      "id": "10 11 19",
      "key": "000100001100019",
      "coords": {
        "x": 10,
        "y": 11,
        "z": 19
      }
    },
    {
      "id": "10 13 32",
      "key": "000100001300032",
      "coords": {
        "x": 10,
        "y": 13,
        "z": 32
      }
    },
    {
      "id": "10 17 20",
      "key": "000100001700020",
      "coords": {
        "x": 10,
        "y": 17,
        "z": 20
      }
    },
    {
      "id": "10 25 10",
      "key": "000100002500010",
      "coords": {
        "x": 10,
        "y": 25,
        "z": 10
      }
    },
    {
      "id": "10 32 7",
      "key": "000100003200007",
      "coords": {
        "x": 10,
        "y": 32,
        "z": 7
      }
    },
    {
      "id": "11 27 19",
      "key": "000110002700019",
      "coords": {
        "x": 11,
        "y": 27,
        "z": 19
      }
    },
    {
      "id": "12 4 27",
      "key": "000120000400027",
      "coords": {
        "x": 12,
        "y": 4,
        "z": 27
      }
    },
    {
      "id": "12 18 7",
      "key": "000120001800007",
      "coords": {
        "x": 12,
        "y": 18,
        "z": 7
      }
    },
    {
      "id": "12 30 27",
      "key": "000120003000027",
      "coords": {
        "x": 12,
        "y": 30,
        "z": 27
      }
    },
    {
      "id": "12 33 27",
      "key": "000120003300027",
      "coords": {
        "x": 12,
        "y": 33,
        "z": 27
      }
    },
    {
      "id": "12 37 39",
      "key": "000120003700039",
      "coords": {
        "x": 12,
        "y": 37,
        "z": 39
      }
    },
    {
      "id": "12 43 23",
      "key": "000120004300023",
      "coords": {
        "x": 12,
        "y": 43,
        "z": 23
      }
    },
    {
      "id": "12 45 20",
      "key": "000120004500020",
      "coords": {
        "x": 12,
        "y": 45,
        "z": 20
      }
    },
    {
      "id": "13 11 11",
      "key": "000130001100011",
      "coords": {
        "x": 13,
        "y": 11,
        "z": 11
      }
    },
    {
      "id": "13 12 30",
      "key": "000130001200030",
      "coords": {
        "x": 13,
        "y": 12,
        "z": 30
      }
    },
    {
      "id": "13 17 7",
      "key": "000130001700007",
      "coords": {
        "x": 13,
        "y": 17,
        "z": 7
      }
    },
    {
      "id": "14 25 44",
      "key": "000140002500044",
      "coords": {
        "x": 14,
        "y": 25,
        "z": 44
      }
    },
    {
      "id": "15 19 4",
      "key": "000150001900004",
      "coords": {
        "x": 15,
        "y": 19,
        "z": 4
      }
    },
    {
      "id": "15 24 31",
      "key": "000150002400031",
      "coords": {
        "x": 15,
        "y": 24,
        "z": 31
      }
    },
    {
      "id": "15 35 9",
      "key": "000150003500009",
      "coords": {
        "x": 15,
        "y": 35,
        "z": 9
      }
    },
    {
      "id": "15 40 10",
      "key": "000150004000010",
      "coords": {
        "x": 15,
        "y": 40,
        "z": 10
      }
    },
    {
      "id": "16 20 44",
      "key": "000160002000044",
      "coords": {
        "x": 16,
        "y": 20,
        "z": 44
      }
    },
    {
      "id": "16 38 21",
      "key": "000160003800021",
      "coords": {
        "x": 16,
        "y": 38,
        "z": 21
      }
    },
    {
      "id": "17 4 19",
      "key": "000170000400019",
      "coords": {
        "x": 17,
        "y": 4,
        "z": 19
      }
    },
    {
      "id": "17 11 38",
      "key": "000170001100038",
      "coords": {
        "x": 17,
        "y": 11,
        "z": 38
      }
    },
    {
      "id": "17 14 16",
      "key": "000170001400016",
      "coords": {
        "x": 17,
        "y": 14,
        "z": 16
      }
    },
    {
      "id": "18 25 24",
      "key": "000180002500024",
      "coords": {
        "x": 18,
        "y": 25,
        "z": 24
      }
    },
    {
      "id": "18 26 12",
      "key": "000180002600012",
      "coords": {
        "x": 18,
        "y": 26,
        "z": 12
      }
    },
    {
      "id": "18 30 4",
      "key": "000180003000004",
      "coords": {
        "x": 18,
        "y": 30,
        "z": 4
      }
    },
    {
      "id": "18 35 35",
      "key": "000180003500035",
      "coords": {
        "x": 18,
        "y": 35,
        "z": 35
      }
    },
    {
      "id": "19 3 22",
      "key": "000190000300022",
      "coords": {
        "x": 19,
        "y": 3,
        "z": 22
      }
    },
    {
      "id": "19 12 5",
      "key": "000190001200005",
      "coords": {
        "x": 19,
        "y": 12,
        "z": 5
      }
    },
    {
      "id": "19 16 8",
      "key": "000190001600008",
      "coords": {
        "x": 19,
        "y": 16,
        "z": 8
      }
    },
    {
      "id": "19 29 2",
      "key": "000190002900002",
      "coords": {
        "x": 19,
        "y": 29,
        "z": 2
      }
    },
    {
      "id": "19 39 16",
      "key": "000190003900016",
      "coords": {
        "x": 19,
        "y": 39,
        "z": 16
      }
    },
    {
      "id": "19 43 12",
      "key": "000190004300012",
      "coords": {
        "x": 19,
        "y": 43,
        "z": 12
      }
    },
    {
      "id": "20 9 37",
      "key": "000200000900037",
      "coords": {
        "x": 20,
        "y": 9,
        "z": 37
      }
    },
    {
      "id": "20 18 42",
      "key": "000200001800042",
      "coords": {
        "x": 20,
        "y": 18,
        "z": 42
      }
    },
    {
      "id": "20 20 20",
      "key": "000200002000020",
      "coords": {
        "x": 20,
        "y": 20,
        "z": 20
      }
    },
    {
      "id": "20 27 12",
      "key": "000200002700012",
      "coords": {
        "x": 20,
        "y": 27,
        "z": 12
      }
    },
    {
      "id": "20 34 3",
      "key": "000200003400003",
      "coords": {
        "x": 20,
        "y": 34,
        "z": 3
      }
    },
    {
      "id": "21 12 18",
      "key": "000210001200018",
      "coords": {
        "x": 21,
        "y": 12,
        "z": 18
      }
    },
    {
      "id": "21 14 41",
      "key": "000210001400041",
      "coords": {
        "x": 21,
        "y": 14,
        "z": 41
      }
    },
    {
      "id": "21 28 27",
      "key": "000210002800027",
      "coords": {
        "x": 21,
        "y": 28,
        "z": 27
      }
    },
    {
      "id": "21 36 21",
      "key": "000210003600021",
      "coords": {
        "x": 21,
        "y": 36,
        "z": 21
      }
    },
    {
      "id": "22 4 34",
      "key": "000220000400034",
      "coords": {
        "x": 22,
        "y": 4,
        "z": 34
      }
    },
    {
      "id": "22 17 26",
      "key": "000220001700026",
      "coords": {
        "x": 22,
        "y": 17,
        "z": 26
      }
    },
    {
      "id": "22 20 45",
      "key": "000220002000045",
      "coords": {
        "x": 22,
        "y": 20,
        "z": 45
      }
    },
    {
      "id": "22 27 30",
      "key": "000220002700030",
      "coords": {
        "x": 22,
        "y": 27,
        "z": 30
      }
    },
    {
      "id": "22 32 30",
      "key": "000220003200030",
      "coords": {
        "x": 22,
        "y": 32,
        "z": 30
      }
    },
    {
      "id": "23 1 28",
      "key": "000230000100028",
      "coords": {
        "x": 23,
        "y": 1,
        "z": 28
      }
    },
    {
      "id": "23 7 28",
      "key": "000230000700028",
      "coords": {
        "x": 23,
        "y": 7,
        "z": 28
      }
    },
    {
      "id": "23 23 15",
      "key": "000230002300015",
      "coords": {
        "x": 23,
        "y": 23,
        "z": 15
      }
    },
    {
      "id": "23 35 33",
      "key": "000230003500033",
      "coords": {
        "x": 23,
        "y": 35,
        "z": 33
      }
    },
    {
      "id": "23 48 22",
      "key": "000230004800022",
      "coords": {
        "x": 23,
        "y": 48,
        "z": 22
      }
    },
    {
      "id": "24 4 14",
      "key": "000240000400014",
      "coords": {
        "x": 24,
        "y": 4,
        "z": 14
      }
    },
    {
      "id": "24 8 36",
      "key": "000240000800036",
      "coords": {
        "x": 24,
        "y": 8,
        "z": 36
      }
    },
    {
      "id": "24 16 42",
      "key": "000240001600042",
      "coords": {
        "x": 24,
        "y": 16,
        "z": 42
      }
    },
    {
      "id": "25 5 34",
      "key": "000250000500034",
      "coords": {
        "x": 25,
        "y": 5,
        "z": 34
      }
    },
    {
      "id": "25 19 5",
      "key": "000250001900005",
      "coords": {
        "x": 25,
        "y": 19,
        "z": 5
      }
    },
    {
      "id": "25 20 42",
      "key": "000250002000042",
      "coords": {
        "x": 25,
        "y": 20,
        "z": 42
      }
    },
    {
      "id": "25 25 18",
      "key": "000250002500018",
      "coords": {
        "x": 25,
        "y": 25,
        "z": 18
      }
    },
    {
      "id": "25 41 24",
      "key": "000250004100024",
      "coords": {
        "x": 25,
        "y": 41,
        "z": 24
      },
      "planets": [
        {
          "id": "25 41 24 1",
          "key": "00025000410002401",
          "orbit": 1,
          "lsn": 9,
          "mining_difficulty": 1.54
        },
        {
          "id": "25 41 24 2",
          "key": "00025000410002402",
          "orbit": 2,
          "name": "Beta",
          "economic_efficiency": 100,
          "lsn": 6,
          "mining_difficulty": 1.03,
          "production_penalty": 46
        },
        {
          "id": "25 41 24 3",
          "key": "00025000410002403",
          "orbit": 3,
          "lsn": 75,
          "mining_difficulty": 3.96
        }
      ],
      "scanned": 3,
      "visited": true
    },
    {
      "id": "26 24 6",
      "key": "000260002400006",
      "coords": {
        "x": 26,
        "y": 24,
        "z": 6
      }
    },
    {
      "id": "26 26 32",
      "key": "000260002600032",
      "coords": {
        "x": 26,
        "y": 26,
        "z": 32
      }
    },
    {
      "id": "26 29 3",
      "key": "000260002900003",
      "coords": {
        "x": 26,
        "y": 29,
        "z": 3
      }
    },
    {
      "id": "26 30 6",
      "key": "000260003000006",
      "coords": {
        "x": 26,
        "y": 30,
        "z": 6
      }
    },
    {
      "id": "26 32 37",
      "key": "000260003200037",
      "coords": {
        "x": 26,
        "y": 32,
        "z": 37
      }
    },
    {
      "id": "26 37 29",
      "key": "000260003700029",
      "coords": {
        "x": 26,
        "y": 37,
        "z": 29
      },
      "planets": [
        {
          "id": "26 37 29 1",
          "key": "00026000370002901",
          "orbit": 1,
          "name": "Gamma",
          "economic_efficiency": 100,
          "lsn": 12,
          "mining_difficulty": 0.96,
          "production_penalty": 92
        }
      ],
      "scanned": 3,
      "visited": true
    },
    {
      "id": "27 6 17",
      "key": "000270000600017",
      "coords": {
        "x": 27,
        "y": 6,
        "z": 17
      }
    },
    {
      "id": "27 11 43",
      "key": "000270001100043",
      "coords": {
        "x": 27,
        "y": 11,
        "z": 43
      }
    },
    {
      "id": "27 34 6",
      "key": "000270003400006",
      "coords": {
        "x": 27,
        "y": 34,
        "z": 6
      }
    },
    {
      "id": "27 43 18",
      "key": "000270004300018",
      "coords": {
        "x": 27,
        "y": 43,
        "z": 18
      }
    },
    {
      "id": "28 4 23",
      "key": "000280000400023",
      "coords": {
        "x": 28,
        "y": 4,
        "z": 23
      }
    },
    {
      "id": "28 13 43",
      "key": "000280001300043",
      "coords": {
        "x": 28,
        "y": 13,
        "z": 43
      }
    },
    {
      "id": "28 16 44",
      "key": "000280001600044",
      "coords": {
        "x": 28,
        "y": 16,
        "z": 44
      }
    },
    {
      "id": "28 22 16",
      "key": "000280002200016",
      "coords": {
        "x": 28,
        "y": 22,
        "z": 16
      }
    },
    {
      "id": "29 23 5",
      "key": "000290002300005",
      "coords": {
        "x": 29,
        "y": 23,
        "z": 5
      }
    },
    {
      "id": "29 31 19",
      "key": "000290003100019",
      "coords": {
        "x": 29,
        "y": 31,
        "z": 19
      }
    },
    {
      "id": "29 36 44",
      "key": "000290003600044",
      "coords": {
        "x": 29,
        "y": 36,
        "z": 44
      }
    },
    {
      "id": "30 8 35",
      "key": "000300000800035",
      "coords": {
        "x": 30,
        "y": 8,
        "z": 35
      }
    },
    {
      "id": "30 9 16",
      "key": "000300000900016",
      "coords": {
        "x": 30,
        "y": 9,
        "z": 16
      }
    },
    {
      "id": "30 22 7",
      "key": "000300002200007",
      "coords": {
        "x": 30,
        "y": 22,
        "z": 7
      }
    },
    {
      "id": "30 28 22",
      "key": "000300002800022",
      "coords": {
        "x": 30,
        "y": 28,
        "z": 22
      }
    },
    {
      "id": "30 30 15",
      "key": "000300003000015",
      "coords": {
        "x": 30,
        "y": 30,
        "z": 15
      }
    },
    {
      "id": "30 33 28",
      "key": "000300003300028",
      "coords": {
        "x": 30,
        "y": 33,
        "z": 28
      }
    },
    {
      "id": "30 41 26",
      "key": "000300004100026",
      "coords": {
        "x": 30,
        "y": 41,
        "z": 26
      },
      "planets": [
        {
          "id": "30 41 26 1",
          "key": "00030000410002601",
          "orbit": 1,
          "lsn": 18,
          "mining_difficulty": 0.45
        },
        {
          "id": "30 41 26 2",
          "key": "00030000410002602",
          "orbit": 2,
          "lsn": 15,
          "mining_difficulty": 0.39
        },
        {
          "id": "30 41 26 3",
          "key": "00030000410002603",
          "orbit": 3,
          "name": "Giznad",
          "home_world": true,
          "available_population_units": 1500,
          "economic_efficiency": 100,
          "mining_difficulty": 2.07,
          "shipyards": 4
        }
      ],
      "scanned": 3,
      "visited": true
    },
    {
      "id": "30 48 28",
      "key": "000300004800028",
      "coords": {
        "x": 30,
        "y": 48,
        "z": 28
      }
    },
    {
      "id": "31 1 23",
      "key": "000310000100023",
      "coords": {
        "x": 31,
        "y": 1,
        "z": 23
      }
    },
    {
      "id": "31 10 43",
      "key": "000310001000043",
      "coords": {
        "x": 31,
        "y": 10,
        "z": 43
      }
    },
    {
      "id": "31 28 36",
      "key": "000310002800036",
      "coords": {
        "x": 31,
        "y": 28,
        "z": 36
      }
    },
    {
      "id": "32 9 23",
      "key": "000320000900023",
      "coords": {
        "x": 32,
        "y": 9,
        "z": 23
      }
    },
    {
      "id": "32 14 34",
      "key": "000320001400034",
      "coords": {
        "x": 32,
        "y": 14,
        "z": 34
      }
    },
    {
      "id": "32 33 43",
      "key": "000320003300043",
      "coords": {
        "x": 32,
        "y": 33,
        "z": 43
      }
    },
    {
      "id": "32 36 43",
      "key": "000320003600043",
      "coords": {
        "x": 32,
        "y": 36,
        "z": 43
      }
    },
    {
      "id": "33 4 23",
      "key": "000330000400023",
      "coords": {
        "x": 33,
        "y": 4,
        "z": 23
      }
    },
    {
      "id": "33 10 15",
      "key": "000330001000015",
      "coords": {
        "x": 33,
        "y": 10,
        "z": 15
      }
    },
    {
      "id": "33 17 18",
      "key": "000330001700018",
      "coords": {
        "x": 33,
        "y": 17,
        "z": 18
      }
    },
    {
      "id": "33 36 6",
      "key": "000330003600006",
      "coords": {
        "x": 33,
        "y": 36,
        "z": 6
      }
    },
    {
      "id": "33 37 43",
      "key": "000330003700043",
      "coords": {
        "x": 33,
        "y": 37,
        "z": 43
      }
    },
    {
      "id": "33 38 27",
      "key": "000330003800027",
      "coords": {
        "x": 33,
        "y": 38,
        "z": 27
      },
      "planets": [
        {
          "id": "33 38 27 1",
          "key": "00033000380002701",
          "orbit": 1,
          "lsn": 78,
          "mining_difficulty": 1.14
        },
        {
          "id": "33 38 27 2",
          "key": "00033000380002702",
          "orbit": 2,
          "lsn": 30,
          "mining_difficulty": 1.49
        },
        {
          "id": "33 38 27 3",
          "key": "00033000380002703",
          "orbit": 3,
          "name": "Alpha",
          "economic_efficiency": 100,
          "lsn": 9,
          "mining_difficulty": 1.43,
          "production_penalty": 69
        },
        {
          "id": "33 38 27 4",
          "key": "00033000380002704",
          "orbit": 4,
          "lsn": 18,
          "mining_difficulty": 1.23
        },
        {
          "id": "33 38 27 5",
          "key": "00033000380002705",
          "orbit": 5,
          "lsn": 45,
          "mining_difficulty": 3.25
        },
        {
          "id": "33 38 27 6",
          "key": "00033000380002706",
          "orbit": 6,
          "lsn": 63,
          "mining_difficulty": 11
        },
        {
          "id": "33 38 27 7",
          "key": "00033000380002707",
          "orbit": 7,
          "lsn": 39,
          "mining_difficulty": 2.2
        }
      ],
      "scanned": 3,
      "visited": true
    },
    {
      "id": "33 40 39",
      "key": "000330004000039",
      "coords": {
        "x": 33,
        "y": 40,
        "z": 39
      }
    },
    {
      "id": "34 9 33",
      "key": "000340000900033",
      "coords": {
        "x": 34,
        "y": 9,
        "z": 33
      }
    },
    {
      "id": "34 13 44",
      "key": "000340001300044",
      "coords": {
        "x": 34,
        "y": 13,
        "z": 44
      }
    },
    {
      "id": "34 18 16",
      "key": "000340001800016",
      "coords": {
        "x": 34,
        "y": 18,
        "z": 16
      }
    },
    {
      "id": "34 21 17",
      "key": "000340002100017",
      "coords": {
        "x": 34,
        "y": 21,
        "z": 17
      }
    },
    {
      "id": "34 27 21",
      "key": "000340002700021",
      "coords": {
        "x": 34,
        "y": 27,
        "z": 21
      }
    },
    {
      "id": "34 28 32",
      "key": "000340002800032",
      "coords": {
        "x": 34,
        "y": 28,
        "z": 32
      }
    },
    {
      "id": "35 3 23",
      "key": "000350000300023",
      "coords": {
        "x": 35,
        "y": 3,
        "z": 23
      }
    },
    {
      "id": "35 23 40",
      "key": "000350002300040",
      "coords": {
        "x": 35,
        "y": 23,
        "z": 40
      }
    },
    {
      "id": "36 6 24",
      "key": "000360000600024",
      "coords": {
        "x": 36,
        "y": 6,
        "z": 24
      }
    },
    {
      "id": "36 19 29",
      "key": "000360001900029",
      "coords": {
        "x": 36,
        "y": 19,
        "z": 29
      }
    },
    {
      "id": "36 24 10",
      "key": "000360002400010",
      "coords": {
        "x": 36,
        "y": 24,
        "z": 10
      }
    },
    {
      "id": "37 15 28",
      "key": "000370001500028",
      "coords": {
        "x": 37,
        "y": 15,
        "z": 28
      }
    },
    {
      "id": "37 17 17",
      "key": "000370001700017",
      "coords": {
        "x": 37,
        "y": 17,
        "z": 17
      }
    },
    {
      "id": "37 29 5",
      "key": "000370002900005",
      "coords": {
        "x": 37,
        "y": 29,
        "z": 5
      }
    },
    {
      "id": "37 37 19",
      "key": "000370003700019",
      "coords": {
        "x": 37,
        "y": 37,
        "z": 19
      }
    },
    {
      "id": "37 41 16",
      "key": "000370004100016",
      "coords": {
        "x": 37,
        "y": 41,
        "z": 16
      }
    },
    {
      "id": "38 13 16",
      "key": "000380001300016",
      "coords": {
        "x": 38,
        "y": 13,
        "z": 16
      }
    },
    {
      "id": "38 15 32",
      "key": "000380001500032",
      "coords": {
        "x": 38,
        "y": 15,
        "z": 32
      }
    },
    {
      "id": "39 6 32",
      "key": "000390000600032",
      "coords": {
        "x": 39,
        "y": 6,
        "z": 32
      }
    },
    {
      "id": "39 16 9",
      "key": "000390001600009",
      "coords": {
        "x": 39,
        "y": 16,
        "z": 9
      }
    },
    {
      "id": "39 19 28",
      "key": "000390001900028",
      "coords": {
        "x": 39,
        "y": 19,
        "z": 28
      }
    },
    {
      "id": "39 25 41",
      "key": "000390002500041",
      "coords": {
        "x": 39,
        "y": 25,
        "z": 41
      }
    },
    {
      "id": "39 29 44",
      "key": "000390002900044",
      "coords": {
        "x": 39,
        "y": 29,
        "z": 44
      }
    },
    {
      "id": "39 30 27",
      "key": "000390003000027",
      "coords": {
        "x": 39,
        "y": 30,
        "z": 27
      }
    },
    {
      "id": "39 34 13",
      "key": "000390003400013",
      "coords": {
        "x": 39,
        "y": 34,
        "z": 13
      }
    },
    {
      "id": "40 18 9",
      "key": "000400001800009",
      "coords": {
        "x": 40,
        "y": 18,
        "z": 9
      }
    },
    {
      "id": "40 21 20",
      "key": "000400002100020",
      "coords": {
        "x": 40,
        "y": 21,
        "z": 20
      }
    },
    {
      "id": "40 23 27",
      "key": "000400002300027",
      "coords": {
        "x": 40,
        "y": 23,
        "z": 27
      }
    },
    {
      "id": "41 8 33",
      "key": "000410000800033",
      "coords": {
        "x": 41,
        "y": 8,
        "z": 33
      }
    },
    {
      "id": "41 18 9",
      "key": "000410001800009",
      "coords": {
        "x": 41,
        "y": 18,
        "z": 9
      }
    },
    {
      "id": "41 24 28",
      "key": "000410002400028",
      "coords": {
        "x": 41,
        "y": 24,
        "z": 28
      }
    },
    {
      "id": "41 28 32",
      "key": "000410002800032",
      "coords": {
        "x": 41,
        "y": 28,
        "z": 32
      }
    },
    {
      "id": "42 23 19",
      "key": "000420002300019",
      "coords": {
        "x": 42,
        "y": 23,
        "z": 19
      }
    },
    {
      "id": "42 25 40",
      "key": "000420002500040",
      "coords": {
        "x": 42,
        "y": 25,
        "z": 40
      }
    },
    {
      "id": "42 34 32",
      "key": "000420003400032",
      "coords": {
        "x": 42,
        "y": 34,
        "z": 32
      }
    },
    {
      "id": "42 38 30",
      "key": "000420003800030",
      "coords": {
        "x": 42,
        "y": 38,
        "z": 30
      }
    },
    {
      "id": "43 10 20",
      "key": "000430001000020",
      "coords": {
        "x": 43,
        "y": 10,
        "z": 20
      }
    },
    {
      "id": "43 14 32",
      "key": "000430001400032",
      "coords": {
        "x": 43,
        "y": 14,
        "z": 32
      }
    },
    {
      "id": "43 16 36",
      "key": "000430001600036",
      "coords": {
        "x": 43,
        "y": 16,
        "z": 36
      }
    },
    {
      "id": "43 18 14",
      "key": "000430001800014",
      "coords": {
        "x": 43,
        "y": 18,
        "z": 14
      }
    },
    {
      "id": "43 32 37",
      "key": "000430003200037",
      "coords": {
        "x": 43,
        "y": 32,
        "z": 37
      }
    },
    {
      "id": "43 39 34",
      "key": "000430003900034",
      "coords": {
        "x": 43,
        "y": 39,
        "z": 34
      }
    },
    {
      "id": "44 21 28",
      "key": "000440002100028",
      "coords": {
        "x": 44,
        "y": 21,
        "z": 28
      }
    },
    {
      "id": "44 26 41",
      "key": "000440002600041",
      "coords": {
        "x": 44,
        "y": 26,
        "z": 41
      }
    },
    {
      "id": "45 26 37",
      "key": "000450002600037",
      "coords": {
        "x": 45,
        "y": 26,
        "z": 37
      }
    },
    {
      "id": "46 17 35",
      "key": "000460001700035",
      "coords": {
        "x": 46,
        "y": 17,
        "z": 35
      }
    },
    {
      "id": "46 25 16",
      "key": "000460002500016",
      "coords": {
        "x": 46,
        "y": 25,
        "z": 16
      }
    },
    {
      "id": "13 13 13",
      "empty": true,
      "ships": []
    }
  ]
}